pytest_record_video/__init__.py
pytest_record_video/__version__.py
pytest_record_video/cmdctl.py
pytest_record_video/plugin.py
pytest_record_video/recording_screen.py
pytest_record_video-2024.10.29.dist-info/METADATA
pytest_record_video-2024.10.29.dist-info/WHEEL
pytest_record_video-2024.10.29.dist-info/entry_points.txt
pytest_record_video-2024.10.29.dist-info/licenses/LICENSE
pytest_record_video-2024.10.29.dist-info/RECORD
